{
  "name": "Brownie",
  "type": "dark",
  "colors": {
    "foreground": "#ad9073",
    "focusBorder": "#ad9073",

    "widget.shadow": "#2c2c2c00",

    "icon.foreground": "#d4a373",

    "selection.background": "#6b2400",

    "textLink.foreground": "#bb7423",

    "badge.background": "#ad9073",
    "badge.foreground": "#222222",

    "titleBar.activeBackground": "#2e2e2e",
    "titleBar.activeForeground": "#d4a373",
    "titleBar.inactiveForeground": "#927252",

    "menu.background": "#2e2e2e",

    "editor.background": "#222222",
    "editor.foreground": "#fff8f1",
    "editor.selectionBackground": "#7a5b50",
    "editor.findMatchBackground": "#bb7423",
    "editor.findMatchHighlightBackground": "#7a5b50",
    "editorCursor.foreground": "#fff8f1",
    "editorGroup.border": "#8a745f",
    "editorLineNumber.foreground": "#7a5b509a",
    "editorLineNumber.activeForeground": "#ad9073",
    "editorWidget.background": "#2e2e2e",
    "editorWidget.foreground": "#d4a373",
    "editorWidget.border": "#bb7423",
    "editorGroupHeader.border": "#2e2e2e",

    "activityBar.background": "#2e2e2e",
    "activityBar.foreground": "#d4a373",
    "activityBar.border": "#222222",
    "activityBarBadge.background": "#bb7423",

    "sideBar.background": "#262626",
    "sideBar.border": "#2e2e2e",
    "sideBarTitle.foreground": "#d4a373",
    "sideBarSectionHeader.background": "#2e2e2e",
    "sideBarSectionHeader.foreground": "#8a745f",
    "sideBarSectionHeader.border": "#222222",

    "button.border": "#ad9073",
    "button.background": "#7a5b50",
    "button.foreground": "#ffdbb7",

    "input.border": "#7a5b50",
    "inputOption.activeBackground": "#7a5b50",
    "inputValidation.errorBackground": "#b94040",
    "inputValidation.errorForeground": "#fff8f1",
    "inputValidation.errorBorder": "#e41f1fd7",

    "list.activeSelectionBackground": "#7a5b50",
    "list.highlightForeground": "#fff8f1",
    "list.filterMatchBackground": "#6b2400",
    "listFilterWidget.background": "#222222",
    "listFilterWidget.outline": "#bb7423",

    "tab.activeBackground": "#222222",
    "tab.activeForeground": "#fff8f1",
    "tab.activeBorder": "#bb7423",
    "tab.border": "#222222",

    "breadcrumb.background": "#222222",
    "breadcrumb.foreground": "#d4a373",

    "editorCodeLens.foreground": "#6e6e6e",

    "statusBar.background": "#8a745f",
    "statusBar.foreground": "#fff8f1",
    "statusBar.debuggingBackground": "#f5594d",
    "statusBar.debuggingForeground": "#2e2e2e",
    "statusBar.noFolderBackground": "#2e2e2e",
    "statusBar.border": "#222222",

    "gitDecoration.modifiedResourceForeground": "#8ceca1a8",
    "gitDecoration.deletedResourceForeground": "#ff7471",
    "gitDecoration.untrackedResourceForeground": "#f5f233c2",
    "gitDecoration.ignoredResourceForeground": "#83a3c2d0",
    "gitDecoration.conflictingResourceForeground": "#ffa4b1e5",

    "notifications.border": "#8a745f",

    "scrollbar.shadow": "#00000000"
  },

  "tokenColors": [
    {
      "name": "Comment",
      "scope": ["comment", "punctuation.definition.comment"],
      "settings": {
        "fontStyle": "italic",
        "foreground": "#646464"
      }
    },
    {
      "name": "Variables",
      "scope": ["variable", "string constant.other.placeholder"],
      "settings": {
        "foreground": "#cf9d6b"
      }
    },
    {
      "name": "Colors",
      "scope": ["constant.other.color"],
      "settings": {
        "foreground": "#fff8f1"
      }
    },
    {
      "name": "Invalid",
      "scope": ["invalid", "invalid.illegal"],
      "settings": {
        "foreground": "#b94040"
      }
    },
    {
      "name": "Keyword, Storage",
      "scope": ["keyword", "storage.type", "storage.modifier"],
      "settings": {
        "foreground": "#bb7423"
      }
    },
    {
      "name": "Operator, Misc",
      "scope": [
        "keyword.control",
        "constant.other.color",
        "punctuation",
        "meta.tag",
        "punctuation.definition.tag",
        "punctuation.separator.inheritance.php",
        "punctuation.definition.tag.html",
        "punctuation.definition.tag.begin.html",
        "punctuation.definition.tag.end.html",
        "punctuation.section.embedded",
        "keyword.other.template",
        "keyword.other.substitution"
      ],
      "settings": {
        "foreground": "#bb7423"
      }
    },
    {
      "name": "Tag",
      "scope": [
        "entity.name.tag",
        "meta.tag.sgml",
        "markup.deleted.git_gutter"
      ],
      "settings": {
        "foreground": "#bb7423"
      }
    },
    {
      "name": "Function, Special Method",
      "scope": [
        "entity.name.function",
        "meta.function-call",
        "variable.function",
        "support.function",
        "keyword.other.special-method"
      ],
      "settings": {
        "foreground": "#ee750b"
      }
    },
    {
      "name": "HTML double quote",
      "scope": [
        "string.quoted.double.html",
        "string.quoted.single.js",
        "string.quoted.double.js",
        "string.template.ts"
      ],
      "settings": {
        "foreground": "#ffdbb7"
      }
    },
    {
      "name": "Block Level Variables",
      "scope": ["meta.block variable.other"],
      "settings": {
        "foreground": "#cf9d6b"
      }
    },
    {
      "name": "Other Variable, String Link",
      "scope": ["support.other.variable", "string.other.link"],
      "settings": {
        "foreground": "#d4a373"
      }
    },
    {
      "name": "Number, Constant, Function Argument, Tag Attribute, Embedded",
      "scope": [
        "constant.numeric",
        "constant.language",
        "support.constant",
        "constant.character",
        "constant.escape",
        "variable.parameter",
        "keyword.other.unit",
        "keyword.other"
      ],
      "settings": {
        "foreground": "#fff8f1"
      }
    },
    {
      "name": "String, Symbols, Inherited Class, Markup Heading",
      "scope": [
        "string",
        "constant.other.symbol",
        "constant.other.key",
        "entity.other.inherited-class",
        "markup.heading",
        "markup.inserted.git_gutter",
        "meta.group.braces.curly constant.other.object.key.js string.unquoted.label.js"
      ],
      "settings": {
        "foreground": "#fff8f1"
      }
    },
    {
      "name": "Class, Support",
      "scope": [
        "entity.name",
        "support.type",
        "support.class",
        "support.other.namespace.use.php",
        "meta.use.php",
        "support.other.namespace.php",
        "markup.changed.git_gutter",
        "support.type.sys-types"
      ],
      "settings": {
        "foreground": "#ffcb6b"
      }
    },
    {
      "name": "Entity Types",
      "scope": ["support.type"],
      "settings": {
        "foreground": "#b2ccd6"
      }
    },
    {
      "name": "CSS Class and Support",
      "scope": [
        "source.css support.type.property-name",
        "source.sass support.type.property-name",
        "source.scss support.type.property-name",
        "source.less support.type.property-name",
        "source.stylus support.type.property-name",
        "source.postcss support.type.property-name"
      ],
      "settings": {
        "foreground": "#ad9073"
      }
    },
    {
      "name": "Sub-methods",
      "scope": [
        "entity.name.module.js",
        "variable.import.parameter.js",
        "variable.other.class.js"
      ],
      "settings": {
        "foreground": "#ff5370"
      }
    },
    {
      "name": "Language methods",
      "scope": ["variable.language"],
      "settings": {
        "fontStyle": "italic",
        "foreground": "#c36866"
      }
    },
    {
      "name": "Language booleans",
      "scope": [
        "constant.language.boolean.true.js",
        "constant.language.boolean.false.js"
      ],
      "settings": {
        "foreground": "#c36866"
      }
    },
    {
      "name": "Object literals",
      "scope": [
        "meta.object-literal.key.js",
        "meta.object.member.js",
        "meta.objectliteral.js",
        "meta.export.default.js"
      ],
      "settings": {
        "foreground": "#ad9073"
      }
    },
    {
      "name": "entity.name.method.js",
      "scope": ["entity.name.method.js"],
      "settings": {
        "fontStyle": "italic",
        "foreground": "#ffdbb7"
      }
    },
    {
      "name": "meta.method.js",
      "scope": [
        "meta.class-method.js entity.name.function.js",
        "variable.function.constructor"
      ],
      "settings": {
        "foreground": "#ffdbb7"
      }
    },
    {
      "name": "Attributes",
      "scope": ["entity.other.attribute-name"],
      "settings": {
        "foreground": "#ad9073"
      }
    },
    {
      "name": "HTML Attributes",
      "scope": [
        "text.html.basic entity.other.attribute-name.html",
        "text.html.basic entity.other.attribute-name"
      ],
      "settings": {
        "fontStyle": "italic",
        "foreground": "#ffcb6b"
      }
    },
    {
      "name": "CSS Classes",
      "scope": ["entity.other.attribute-name.class"],
      "settings": {
        "foreground": "#ffcb6b"
      }
    },
    {
      "name": "CSS ID's",
      "scope": ["source.sass keyword.control"],
      "settings": {
        "foreground": "#ffdbb7"
      }
    },
    {
      "name": "Inserted",
      "scope": ["markup.inserted"],
      "settings": {
        "foreground": "#c3e88d"
      }
    },
    {
      "name": "Deleted",
      "scope": ["markup.deleted"],
      "settings": {
        "foreground": "#ff5370"
      }
    },
    {
      "name": "Changed",
      "scope": ["markup.changed"],
      "settings": {
        "foreground": "#c792ea"
      }
    },
    {
      "name": "Regular Expressions",
      "scope": ["string.regexp"],
      "settings": {
        "foreground": "#89ddff"
      }
    },
    {
      "name": "Escape Characters",
      "scope": ["constant.character.escape"],
      "settings": {
        "foreground": "#89ddff"
      }
    },
    {
      "name": "URL",
      "scope": ["*url*", "*link*", "*uri*"],
      "settings": {
        "fontStyle": "underline"
      }
    },
    {
      "name": "Decorators",
      "scope": [
        "tag.decorator.js entity.name.tag.js",
        "tag.decorator.js punctuation.definition.tag.js"
      ],
      "settings": {
        "fontStyle": "italic",
        "foreground": "#ffdbb7"
      }
    },
    {
      "name": "ES7 Bind Operator",
      "scope": [
        "source.js constant.other.object.key.js string.unquoted.label.js"
      ],
      "settings": {
        "fontStyle": "italic",
        "foreground": "#ff5370"
      }
    },
    {
      "name": "JSON Key - Level 0",
      "scope": [
        "source.json meta.structure.dictionary.json support.type.property-name.json"
      ],
      "settings": {
        "foreground": "#ee750b"
      }
    },
    {
      "name": "JSON Key - Level 1",
      "scope": [
        "source.json meta.structure.dictionary.json meta.structure.dictionary.value.json meta.structure.dictionary.json support.type.property-name.json"
      ],
      "settings": {
        "foreground": "#bb7423"
      }
    },
    {
      "name": "JSON Key - Level 2",
      "scope": [
        "source.json meta.structure.dictionary.json meta.structure.dictionary.value.json meta.structure.dictionary.json meta.structure.dictionary.value.json meta.structure.dictionary.json support.type.property-name.json"
      ],
      "settings": {
        "foreground": "#ad9073"
      }
    },
    {
      "name": "JSON Key - Level 3",
      "scope": [
        "source.json meta.structure.dictionary.json meta.structure.dictionary.value.json meta.structure.dictionary.json meta.structure.dictionary.value.json meta.structure.dictionary.json meta.structure.dictionary.value.json meta.structure.dictionary.json support.type.property-name.json"
      ],
      "settings": {
        "foreground": "#cf9d6b"
      }
    },
    {
      "name": "JSON Key - Level 4",
      "scope": [
        "source.json meta.structure.dictionary.json meta.structure.dictionary.value.json meta.structure.dictionary.json meta.structure.dictionary.value.json meta.structure.dictionary.json meta.structure.dictionary.value.json meta.structure.dictionary.json meta.structure.dictionary.value.json meta.structure.dictionary.json support.type.property-name.json"
      ],
      "settings": {
        "foreground": "#ffdbb7"
      }
    },
    {
      "name": "JSON Key - Level 5",
      "scope": [
        "source.json meta.structure.dictionary.json meta.structure.dictionary.value.json meta.structure.dictionary.json meta.structure.dictionary.value.json meta.structure.dictionary.json meta.structure.dictionary.value.json meta.structure.dictionary.json meta.structure.dictionary.value.json meta.structure.dictionary.json meta.structure.dictionary.value.json meta.structure.dictionary.json support.type.property-name.json"
      ],
      "settings": {
        "foreground": "#ffcb6b"
      }
    },
    {
      "name": "JSON Key - Level 6",
      "scope": [
        "source.json meta.structure.dictionary.json meta.structure.dictionary.value.json meta.structure.dictionary.json meta.structure.dictionary.value.json meta.structure.dictionary.json meta.structure.dictionary.value.json meta.structure.dictionary.json meta.structure.dictionary.value.json meta.structure.dictionary.json meta.structure.dictionary.value.json meta.structure.dictionary.json meta.structure.dictionary.value.json meta.structure.dictionary.json support.type.property-name.json"
      ],
      "settings": {
        "foreground": "#ad9073"
      }
    },
    {
      "name": "JSON Key - Level 7",
      "scope": [
        "source.json meta.structure.dictionary.json meta.structure.dictionary.value.json meta.structure.dictionary.json meta.structure.dictionary.value.json meta.structure.dictionary.json meta.structure.dictionary.value.json meta.structure.dictionary.json meta.structure.dictionary.value.json meta.structure.dictionary.json meta.structure.dictionary.value.json meta.structure.dictionary.json meta.structure.dictionary.value.json meta.structure.dictionary.json meta.structure.dictionary.value.json meta.structure.dictionary.json support.type.property-name.json"
      ],
      "settings": {
        "foreground": "#ad9073"
      }
    },
    {
      "name": "JSON Key - Level 8",
      "scope": [
        "source.json meta.structure.dictionary.json meta.structure.dictionary.value.json meta.structure.dictionary.json meta.structure.dictionary.value.json meta.structure.dictionary.json meta.structure.dictionary.value.json meta.structure.dictionary.json meta.structure.dictionary.value.json meta.structure.dictionary.json meta.structure.dictionary.value.json meta.structure.dictionary.json meta.structure.dictionary.value.json meta.structure.dictionary.json meta.structure.dictionary.value.json meta.structure.dictionary.json meta.structure.dictionary.value.json meta.structure.dictionary.json support.type.property-name.json"
      ],
      "settings": {
        "foreground": "#bb7423"
      }
    },
    {
      "name": "Markdown - Plain",
      "scope": [
        "text.html.markdown",
        "punctuation.definition.list_item.markdown"
      ],
      "settings": {
        "foreground": "#fff8f1"
      }
    },
    {
      "name": "Markdown - Markup Raw Inline",
      "scope": ["text.html.markdown markup.inline.raw.markdown"],
      "settings": {
        "foreground": "#c792ea"
      }
    },
    {
      "name": "Markdown - Markup Raw Inline Punctuation",
      "scope": [
        "text.html.markdown markup.inline.raw.markdown punctuation.definition.raw.markdown"
      ],
      "settings": {
        "foreground": "#646464"
      }
    },
    {
      "name": "Markdown - Heading",
      "scope": [
        "markdown.heading",
        "markup.heading | markup.heading entity.name",
        "markup.heading.markdown punctuation.definition.heading.markdown"
      ],
      "settings": {
        "foreground": "#ee750b"
      }
    },
    {
      "name": "Markup - Italic",
      "scope": ["markup.italic"],
      "settings": {
        "fontStyle": "italic",
        "foreground": "#cf9d6b"
      }
    },
    {
      "name": "Markup - Bold",
      "scope": ["markup.bold", "markup.bold string"],
      "settings": {
        "fontStyle": "bold",
        "foreground": "#cf9d6b"
      }
    },
    {
      "name": "Markup - Bold-Italic",
      "scope": [
        "markup.bold markup.italic",
        "markup.italic markup.bold",
        "markup.quote markup.bold",
        "markup.bold markup.italic string",
        "markup.italic markup.bold string",
        "markup.quote markup.bold string"
      ],
      "settings": {
        "fontStyle": "bold",
        "foreground": "#cf9d6b"
      }
    },
    {
      "name": "Markup - Underline",
      "scope": ["markup.underline"],
      "settings": {
        "fontStyle": "underline",
        "foreground": "#AD9073"
      }
    },
    {
      "name": "Markdown - Blockquote",
      "scope": ["markup.quote punctuation.definition.blockquote.markdown"],
      "settings": {
        "foreground": "#646464"
      }
    },
    {
      "name": "Markup - Quote",
      "scope": ["markup.quote"],
      "settings": {
        "fontStyle": "italic"
      }
    },
    {
      "name": "Markdown - Link",
      "scope": ["string.other.link.title.markdown"],
      "settings": {
        "foreground": "#ffdbb7"
      }
    },
    {
      "name": "Markdown - Link Description",
      "scope": ["string.other.link.description.title.markdown"],
      "settings": {
        "foreground": "#c792ea"
      }
    },
    {
      "name": "Markdown - Link Anchor",
      "scope": ["constant.other.reference.link.markdown"],
      "settings": {
        "foreground": "#ffcb6b"
      }
    },
    {
      "name": "Markup - Raw Block",
      "scope": ["markup.raw.block"],
      "settings": {
        "foreground": "#c792ea"
      }
    },
    {
      "name": "Markdown - Raw Block Fenced",
      "scope": ["markup.raw.block.fenced.markdown"],
      "settings": {
        "foreground": "#00000050"
      }
    },
    {
      "name": "Markdown - Fenced Bode Block",
      "scope": ["punctuation.definition.fenced.markdown"],
      "settings": {
        "foreground": "#00000050"
      }
    },
    {
      "name": "Markdown - Fenced Bode Block Variable",
      "scope": [
        "markup.raw.block.fenced.markdown",
        "variable.language.fenced.markdown",
        "punctuation.section.class.end"
      ],
      "settings": {
        "foreground": "#fff8f1"
      }
    },
    {
      "name": "Markdown - Fenced Language",
      "scope": ["variable.language.fenced.markdown"],
      "settings": {
        "foreground": "#646464"
      }
    },
    {
      "name": "Markdown - Separator",
      "scope": ["meta.separator"],
      "settings": {
        "fontStyle": "bold",
        "foreground": "#646464"
      }
    },
    {
      "name": "Markup - Table",
      "scope": ["markup.table"],
      "settings": {
        "foreground": "#fff8f1"
      }
    }
  ]
}
